rincewindlogger/__init__.py
rincewindlogger/rincewindlogger.py
rincewindlogger-0.1.4.dist-info/METADATA
rincewindlogger-0.1.4.dist-info/WHEEL
rincewindlogger-0.1.4.dist-info/RECORD
