Metadata-Version: 2.1
Name: rincewindlogger
Version: 0.1.4
Summary: A module to handle in a standard way for all my cli python scripts.
License: MIT
Author: James Ainslie
Requires-Python: >=3.12,<4.0
Classifier: License :: OSI Approved :: MIT License
Classifier: Programming Language :: Python :: 3
Classifier: Programming Language :: Python :: 3.12
